k3handy/__init__.py
k3handy/cmdutil.py
k3handy/path.py
k3handy-0.1.12.dist-info/licenses/LICENSE
k3handy-0.1.12.dist-info/METADATA
k3handy-0.1.12.dist-info/WHEEL
k3handy-0.1.12.dist-info/top_level.txt
k3handy-0.1.12.dist-info/RECORD
